{"name": "\u516b\u5e74\u7ea7\u4e0a\u518c", "pages": [{"link": "", "page": 0, "title": "\u81f4\u8001\u5e08\u4eec"}, {"link": "", "page": 0, "title": "\u76ee\u5f55"}, {"link": "", "page": 0, "title": "<strong>\u7b2c\u4e00\u5355\u5143\u5355\u5143\u8bf4\u660e</strong>"}, {"link": "", "page": 0, "title": "1\u3000\u65b0\u95fb\u4e24\u5219"}, {"link": "", "page": 0, "title": "2\u3000\u82a6\u82b1\u8361"}, {"link": "", "page": 0, "title": "3\u3000\u8721\u70db"}, {"link": "", "page": 0, "title": "4\u3000\u5c31\u82f1\u6cd5\u8054\u519b\u8fdc\u5f81\u4e2d\u56fd\u81f4\u5e03\u7279\u52d2\u4e0a\u5c09\u7684\u4fe1"}, {"link": "", "page": 0, "title": "5\u3000\u4eb2\u7231\u7684\u7238\u7238\u5988\u5988"}, {"link": "", "page": 0, "title": "\u7efc\u5408\u6027\u5b66\u4e60\u00b7\u5199\u4f5c\u00b7\u53e3\u8bed\u4ea4\u9645\uff1a\u4e16\u754c\u4f55\u65f6\u94f8\u5251\u4e3a\u7281<p></p>"}, {"link": "", "page": 0, "title": "<strong>\u7b2c\u4e8c\u5355\u5143\u5355\u5143\u8bf4\u660e</strong>"}, {"link": "", "page": 0, "title": "6\u3000\u963f\u957f\u4e0e\u300a\u5c71\u6d77\u7ecf\u300b"}, {"link": "http://www.pep.com.cn/czyw/jszx/tbjxzy/jsys/bs/201008oldimages/pic_88871.jpg", "page": 0, "title": "7\u3000\u80cc\u5f71"}, {"link": "", "page": 0, "title": "8\u3000\u53f0\u9636"}, {"link": "", "page": 0, "title": "9\u3000\u8001\u738b"}, {"link": "", "page": 0, "title": "10\u3000\u4fe1\u5ba2"}, {"link": "", "page": 0, "title": "\u5199\u4f5c\u00b7\u53e3\u8bed\u4ea4\u9645\u00b7\u7efc\u5408\u6027\u5b66\u4e60\uff1a\u8ba9\u4e16\u754c\u5145\u6ee1\u7231<p></p>"}, {"link": "", "page": 0, "title": "<strong>\u7b2c\u4e09\u5355\u5143\u5355\u5143\u8bf4\u660e</strong>"}, {"link": "", "page": 0, "title": "11\u3000\u4e2d\u56fd\u77f3\u62f1\u6865"}, {"link": "", "page": 0, "title": "12\u3000\u6865\u4e4b\u7f8e"}, {"link": "", "page": 0, "title": "13\u3000\u82cf\u5dde\u56ed\u6797"}, {"link": "", "page": 0, "title": "14\u3000\u6545\u5bab\u535a\u7269\u9662"}, {"link": "", "page": 0, "title": "15\u3000\u8bf4\u201c\u5c4f\u201d"}, {"link": "", "page": 0, "title": "\u7efc\u5408\u6027\u5b66\u4e60\u00b7\u5199\u4f5c\u00b7\u53e3\u8bed\u4ea4\u9645\uff1a\u8bf4\u4e0d\u5c3d\u7684\u6865<p></p>"}, {"link": "", "page": 0, "title": "<strong>\u7b2c\u56db\u5355\u5143\u5355\u5143\u8bf4\u660e</strong>"}, {"link": "", "page": 0, "title": "16\u3000\u5927\u81ea\u7136\u7684\u8bed\u8a00"}, {"link": "", "page": 0, "title": "17\u3000\u5947\u5999\u7684\u514b\u9686"}, {"link": "", "page": 0, "title": "18\u3000\u963f\u897f\u83ab\u592b\u77ed\u6587\u4e24\u7bc7"}, {"link": "", "page": 0, "title": "19\u3000\u751f\u7269\u5165\u4fb5\u8005"}, {"link": "", "page": 0, "title": "20\u3000\u4f60\u4e00\u5b9a\u4f1a\u542c\u89c1\u7684"}, {"link": "", "page": 0, "title": "\u5199\u4f5c\u00b7\u53e3\u8bed\u4ea4\u9645\u00b7\u7efc\u5408\u6027\u5b66\u4e60\uff1a\u8d70\u4e0a\u8fa9\u8bba\u53f0<p></p>"}, {"link": "", "page": 0, "title": "<strong>\u7b2c\u4e94\u5355\u5143\u5355\u5143\u8bf4\u660e</strong>"}, {"link": "", "page": 0, "title": "21\u3000\u6843\u82b1\u6e90\u8bb0"}, {"link": "", "page": 0, "title": "22\u3000\u77ed\u6587\u4e24\u7bc7"}, {"link": "http://www.pep.com.cn/czyw/jszx/tbjxzy/jsys/bs/201008oldimages/pic_88994.jpg", "page": 0, "title": "23\u3000\u6838\u821f\u8bb0"}, {"link": "", "page": 0, "title": "24\u3000\u5927\u9053\u4e4b\u884c\u4e5f"}, {"link": "http://www.pep.com.cn/czyw/jszx/tbjxzy/jsys/bs/201008oldimages/pic_88997.jpg", "page": 0, "title": "25\u3000\u675c\u752b\u8bd7\u4e09\u9996"}, {"link": "", "page": 0, "title": "\u7efc\u5408\u6027\u5b66\u4e60\u00b7\u5199\u4f5c\u00b7\u53e3\u8bed\u4ea4\u9645\uff1a\u83b2\u6587\u5316\u7684\u9b45\u529b<p></p>"}, {"link": "", "page": 0, "title": "<strong>\u7b2c\u516d\u5355\u5143\u5355\u5143\u8bf4\u660e</strong>"}, {"link": "", "page": 0, "title": "26\u3000\u4e09\u5ce1"}, {"link": "", "page": 0, "title": "27\u3000\u77ed\u6587\u4e24\u7bc7"}, {"link": "", "page": 0, "title": "28\u3000\u89c2\u6f6e"}, {"link": "", "page": 0, "title": "29\u3000\u6e56\u5fc3\u4ead\u770b\u96ea"}, {"link": "", "page": 0, "title": "30\u3000\u8bd7\u56db\u9996"}, {"link": "", "page": 0, "title": "\u5199\u4f5c\u00b7\u53e3\u8bed\u4ea4\u9645\u00b7\u7efc\u5408\u6027\u5b66\u4e60\uff1a\u600e\u6837\u641c\u96c6\u8d44\u6599<p></p> "}, {"link": "", "page": 0, "title": "\u4e49\u52a1\u8bfe\u7a0b\u6807\u51c6\u5b9e\u9a8c\u6559\u79d1\u4e66\u8bed\u6587\u516b\u5e74\u7ea7\u4e0a\u518c\u6559\u5e08\u6559\u5b66\u7528\u4e66"}, {"link": "", "page": 0, "title": "\u81f4\u8001\u5e08\u4eec"}, {"link": "", "page": 0, "title": "\u76ee\u5f55"}, {"link": "", "page": 0, "title": "<strong>\u7b2c\u4e00\u5355\u5143\u5355\u5143\u8bf4\u660e</strong>"}, {"link": "", "page": 0, "title": "1\u3000\u65b0\u95fb\u4e24\u5219"}, {"link": "", "page": 0, "title": "2\u3000\u82a6\u82b1\u8361"}, {"link": "", "page": 0, "title": "3\u3000\u8721\u70db"}, {"link": "", "page": 0, "title": "4\u3000\u5c31\u82f1\u6cd5\u8054\u519b\u8fdc\u5f81\u4e2d\u56fd\u81f4\u5e03\u7279\u52d2\u4e0a\u5c09\u7684\u4fe1"}, {"link": "", "page": 0, "title": "5\u3000\u4eb2\u7231\u7684\u7238\u7238\u5988\u5988"}, {"link": "", "page": 0, "title": "\u7efc\u5408\u6027\u5b66\u4e60\u00b7\u5199\u4f5c\u00b7\u53e3\u8bed\u4ea4\u9645\uff1a\u4e16\u754c\u4f55\u65f6\u94f8\u5251\u4e3a\u7281<p></p>"}, {"link": "", "page": 0, "title": "<strong>\u7b2c\u4e8c\u5355\u5143\u5355\u5143\u8bf4\u660e</strong>"}, {"link": "", "page": 0, "title": "6\u3000\u963f\u957f\u4e0e\u300a\u5c71\u6d77\u7ecf\u300b"}, {"link": "http://www.pep.com.cn/czyw/jszx/tbjxzy/jsys/bs/201008oldimages/pic_88871.jpg", "page": 0, "title": "7\u3000\u80cc\u5f71"}, {"link": "", "page": 0, "title": "8\u3000\u53f0\u9636"}, {"link": "", "page": 0, "title": "9\u3000\u8001\u738b"}, {"link": "", "page": 0, "title": "10\u3000\u4fe1\u5ba2"}, {"link": "", "page": 0, "title": "\u5199\u4f5c\u00b7\u53e3\u8bed\u4ea4\u9645\u00b7\u7efc\u5408\u6027\u5b66\u4e60\uff1a\u8ba9\u4e16\u754c\u5145\u6ee1\u7231<p></p>"}, {"link": "", "page": 0, "title": "<strong>\u7b2c\u4e09\u5355\u5143\u5355\u5143\u8bf4\u660e</strong>"}, {"link": "", "page": 0, "title": "11\u3000\u4e2d\u56fd\u77f3\u62f1\u6865"}, {"link": "", "page": 0, "title": "12\u3000\u6865\u4e4b\u7f8e"}, {"link": "", "page": 0, "title": "13\u3000\u82cf\u5dde\u56ed\u6797"}, {"link": "", "page": 0, "title": "14\u3000\u6545\u5bab\u535a\u7269\u9662"}, {"link": "", "page": 0, "title": "15\u3000\u8bf4\u201c\u5c4f\u201d"}, {"link": "", "page": 0, "title": "\u7efc\u5408\u6027\u5b66\u4e60\u00b7\u5199\u4f5c\u00b7\u53e3\u8bed\u4ea4\u9645\uff1a\u8bf4\u4e0d\u5c3d\u7684\u6865<p></p>"}, {"link": "", "page": 0, "title": "<strong>\u7b2c\u56db\u5355\u5143\u5355\u5143\u8bf4\u660e</strong>"}, {"link": "", "page": 0, "title": "16\u3000\u5927\u81ea\u7136\u7684\u8bed\u8a00"}, {"link": "", "page": 0, "title": "17\u3000\u5947\u5999\u7684\u514b\u9686"}, {"link": "", "page": 0, "title": "18\u3000\u963f\u897f\u83ab\u592b\u77ed\u6587\u4e24\u7bc7"}, {"link": "", "page": 0, "title": "19\u3000\u751f\u7269\u5165\u4fb5\u8005"}, {"link": "", "page": 0, "title": "20\u3000\u4f60\u4e00\u5b9a\u4f1a\u542c\u89c1\u7684"}, {"link": "", "page": 0, "title": "\u5199\u4f5c\u00b7\u53e3\u8bed\u4ea4\u9645\u00b7\u7efc\u5408\u6027\u5b66\u4e60\uff1a\u8d70\u4e0a\u8fa9\u8bba\u53f0<p></p>"}, {"link": "", "page": 0, "title": "<strong>\u7b2c\u4e94\u5355\u5143\u5355\u5143\u8bf4\u660e</strong>"}, {"link": "", "page": 0, "title": "21\u3000\u6843\u82b1\u6e90\u8bb0"}, {"link": "", "page": 0, "title": "22\u3000\u77ed\u6587\u4e24\u7bc7"}, {"link": "http://www.pep.com.cn/czyw/jszx/tbjxzy/jsys/bs/201008oldimages/pic_88994.jpg", "page": 0, "title": "23\u3000\u6838\u821f\u8bb0"}, {"link": "", "page": 0, "title": "24\u3000\u5927\u9053\u4e4b\u884c\u4e5f"}, {"link": "http://www.pep.com.cn/czyw/jszx/tbjxzy/jsys/bs/201008oldimages/pic_88997.jpg", "page": 0, "title": "25\u3000\u675c\u752b\u8bd7\u4e09\u9996"}, {"link": "", "page": 0, "title": "\u7efc\u5408\u6027\u5b66\u4e60\u00b7\u5199\u4f5c\u00b7\u53e3\u8bed\u4ea4\u9645\uff1a\u83b2\u6587\u5316\u7684\u9b45\u529b<p></p>"}, {"link": "", "page": 0, "title": "<strong>\u7b2c\u516d\u5355\u5143\u5355\u5143\u8bf4\u660e</strong>"}, {"link": "", "page": 0, "title": "26\u3000\u4e09\u5ce1"}, {"link": "", "page": 0, "title": "27\u3000\u77ed\u6587\u4e24\u7bc7"}, {"link": "", "page": 0, "title": "28\u3000\u89c2\u6f6e"}, {"link": "", "page": 0, "title": "29\u3000\u6e56\u5fc3\u4ead\u770b\u96ea"}, {"link": "", "page": 0, "title": "30\u3000\u8bd7\u56db\u9996"}, {"link": "", "page": 0, "title": "\u5199\u4f5c\u00b7\u53e3\u8bed\u4ea4\u9645\u00b7\u7efc\u5408\u6027\u5b66\u4e60\uff1a\u600e\u6837\u641c\u96c6\u8d44\u6599<p></p> "}]}