{"name": "\u5206\u5b50\u4e0e\u7ec6\u80de", "pages": [{"link": "http://www.pep.com.cn/gzsw/jshzhx/tbziy/kbshy/jsjb/bxyi/201009/W020100913380358420270.jpg", "page": 0, "title": "\u5c01\u9762"}, {"link": "http://www.pep.com.cn/gzsw/jshzhx/tbziy/kbshy/jsjb/bxyi/201009/W020100913380357022544.jpg", "page": 0, "title": "\u6249\u9875"}, {"link": "http://www.pep.com.cn/gzsw/jshzhx/tbziy/kbshy/jsjb/bxyi/201009/W020100913380355922011.jpg", "page": 0, "title": "\u7248\u6743\u9875"}, {"link": "http://www.pep.com.cn/gzsw/jshzhx/tbziy/kbshy/jsjb/bxyi/201009/W020100913380344527870.jpg", "page": 0, "title": "\u7f16\u5199\u4eba\u5458"}, {"link": "http://www.pep.com.cn/gzsw/jshzhx/tbziy/kbshy/jsjb/bxyi/201009/W020100913380343429712.jpg", "page": 0, "title": "\u76ee\u5f55"}, {"link": "http://www.pep.com.cn/gzsw/jshzhx/tbziy/kbshy/jsjb/bxyi/201009/W020100913380341240983.jpg", "page": 0, "title": "\u76ee\u5f55"}, {"link": "http://www.pep.com.cn/gzsw/jshzhx/tbziy/kbshy/jsjb/bxyi/201009/W020100913380339528133.jpg", "page": 0, "title": "<strong>\u79d1\u5b66\u5bb6\u8bbf\u8c08\u3000\u63a2\u7d22\u751f\u7269\u5927\u5206\u5b50\u7684\u5965\u79d8</strong>\u3000"}, {"link": "http://www.pep.com.cn/oldimages/pic_133352.jpg", "page": 0, "title": "\u79d1\u5b66\u5bb6\u8bbf\u8c08\uff082\uff09"}, {"link": "http://www.pep.com.cn/oldimages/pic_133353.jpg", "page": 0, "title": "\u79d1\u5b66\u5bb6\u8bbf\u8c08\uff083\uff09"}, {"link": "http://www.pep.com.cn/gzsw/jshzhx/tbziy/kbshy/jsjb/bxyi/201009/W020100913380336705789.jpg", "page": 0, "title": "<strong>\u7b2c1\u7ae0\u3000\u8d70\u8fd1\u7ec6\u80de</strong>"}, {"link": "http://www.pep.com.cn/gzsw/jshzhx/tbziy/kbshy/jsjb/bxyi/201009/W020100913380335300565.jpg", "page": 0, "title": "\u3000\u3000\u7b2c1\u8282\u3000\u4ece\u751f\u7269\u5708\u5230\u7ec6\u80de"}, {"link": "http://www.pep.com.cn/oldimages/pic_133216.jpg", "page": 0, "title": "\u7b2c1\u8282\u4ece\u751f\u7269\u5708\u5230\u7ec6\u80de\uff082\uff09"}, {"link": "http://www.pep.com.cn/oldimages/pic_133217.jpg", "page": 0, "title": "\u7b2c1\u8282\u4ece\u751f\u7269\u5708\u5230\u7ec6\u80de\uff083\uff09"}, {"link": "http://www.pep.com.cn/oldimages/pic_133218.jpg", "page": 0, "title": "\u7b2c1\u8282\u4ece\u751f\u7269\u5708\u5230\u7ec6\u80de\uff084\uff09"}, {"link": "http://www.pep.com.cn/oldimages/pic_133219.jpg", "page": 0, "title": "\u7b2c1\u8282\u4ece\u751f\u7269\u5708\u5230\u7ec6\u80de\uff085\uff09"}, {"link": "http://www.pep.com.cn/gzsw/jshzhx/tbziy/kbshy/jsjb/bxyi/201009/W020100913380328893464.jpg", "page": 0, "title": "\u3000\u3000\u7b2c2\u8282\u3000\u7ec6\u80de\u7684\u591a\u6837\u6027\u548c\u7edf\u4e00\u6027"}, {"link": "", "page": 0, "title": "\u7b2c2\u8282\u7ec6\u80de\u7684\u591a\u6837\u6027\u548c\u7edf\u4e00\u6027\uff082\uff09"}, {"link": "http://www.pep.com.cn/oldimages/pic_133221.jpg", "page": 0, "title": "\u7b2c2\u8282\u7ec6\u80de\u7684\u591a\u6837\u6027\u548c\u7edf\u4e00\u6027\uff082\uff09"}, {"link": "http://www.pep.com.cn/oldimages/pic_133222.jpg", "page": 0, "title": "\u7b2c2\u8282\u7ec6\u80de\u7684\u591a\u6837\u6027\u548c\u7edf\u4e00\u6027\uff083\uff09"}, {"link": "http://www.pep.com.cn/oldimages/pic_133223.jpg", "page": 0, "title": "\u7b2c2\u8282\u7ec6\u80de\u7684\u591a\u6837\u6027\u548c\u7edf\u4e00\u6027\uff084\uff09"}, {"link": "http://www.pep.com.cn/oldimages/pic_133224.jpg", "page": 0, "title": "\u7b2c2\u8282\u7ec6\u80de\u7684\u591a\u6837\u6027\u548c\u7edf\u4e00\u6027\uff085\uff09"}, {"link": "http://www.pep.com.cn/gzsw/jshzhx/tbziy/kbshy/jsjb/bxyi/201009/W020100913380319996320.jpg", "page": 0, "title": "\u3000\u3000\u79d1\u5b66\u524d\u6cbf\u3000\u7ec4\u88c5\u7ec6\u80de"}, {"link": "http://www.pep.com.cn/oldimages/pic_133226.jpg", "page": 0, "title": "\u672c\u7ae0\u5c0f\u7ed3"}, {"link": "http://www.pep.com.cn/oldimages/pic_133227.jpg", "page": 0, "title": "\u81ea\u6211\u68c0\u6d4b"}, {"link": "http://www.pep.com.cn/gzsw/jshzhx/tbziy/kbshy/jsjb/bxyi/201009/W020100913380315140607.jpg", "page": 0, "title": "<strong>\u7b2c2\u7ae0\u3000\u7ec4\u6210\u7ec6\u80de\u7684\u5206\u5b50</strong>"}, {"link": "http://www.pep.com.cn/gzsw/jshzhx/tbziy/kbshy/jsjb/bxyi/201009/W020100913380313746299.jpg", "page": 0, "title": "\u3000\u3000\u7b2c1\u8282\u3000\u7ec6\u80de\u4e2d\u7684\u5143\u7d20\u548c\u5316\u5408\u7269"}, {"link": "http://www.pep.com.cn/oldimages/pic_133230.jpg", "page": 0, "title": "\u7b2c1\u8282\u7ec6\u80de\u4e2d\u7684\u5143\u7d20\u548c\u5316\u5408\u7269\uff082\uff09"}, {"link": "http://www.pep.com.cn/oldimages/pic_133231.jpg", "page": 0, "title": "\u7b2c1\u8282\u7ec6\u80de\u4e2d\u7684\u5143\u7d20\u548c\u5316\u5408\u7269\uff083\uff09"}, {"link": "http://www.pep.com.cn/oldimages/pic_133232.jpg", "page": 0, "title": "\u7b2c1\u8282\u7ec6\u80de\u4e2d\u7684\u5143\u7d20\u548c\u5316\u5408\u7269\uff084\uff09"}, {"link": "http://www.pep.com.cn/gzsw/jshzhx/tbziy/kbshy/jsjb/bxyi/201009/W020100913380308748804.jpg", "page": 0, "title": "\u3000\u3000\u7b2c2\u8282\u3000\u751f\u547d\u6d3b\u52a8\u7684\u4e3b\u8981\u627f\u62c5\u8005"}, {"link": "http://www.pep.com.cn/oldimages/pic_133234.jpg", "page": 0, "title": "\u7b2c2\u8282\u751f\u547d\u6d3b\u52a8\u7684\u4e3b\u8981\u627f\u62c5\u8005"}, {"link": "http://www.pep.com.cn/oldimages/pic_133235.jpg", "page": 0, "title": "\u7b2c2\u8282\u751f\u547d\u6d3b\u52a8\u7684\u4e3b\u8981\u627f\u62c5\u8005"}, {"link": "http://www.pep.com.cn/oldimages/pic_133236.jpg", "page": 0, "title": "\u7b2c2\u8282\u751f\u547d\u6d3b\u52a8\u7684\u4e3b\u8981\u627f\u62c5\u8005"}, {"link": "http://www.pep.com.cn/gzsw/jshzhx/tbziy/kbshy/jsjb/bxyi/201009/W020100913380303740215.jpg", "page": 0, "title": "\u3000\u3000\u79d1\u5b66\u53f2\u8bdd\u3000\u4e16\u754c\u4e0a\u7b2c\u4e00\u4e2a\u4eba\u5de5\u5408\u6210\u86cb\u767d\u8d28\u7684\u8bde\u751f"}, {"link": "http://www.pep.com.cn/oldimages/pic_133238.jpg", "page": 0, "title": "\u79d1\u5b66\u524d\u6cbf\u56fd\u9645\u4eba\u7c7b\u86cb\u767d\u8d28\u7ec4\u8ba1\u5212"}, {"link": "http://www.pep.com.cn/gzsw/jshzhx/tbziy/kbshy/jsjb/bxyi/201009/W020100913380300301249.jpg", "page": 0, "title": "\u3000\u3000\u7b2c3\u8282\u3000\u9057\u4f20\u4fe1\u606f\u7684\u643a\u5e26\u8005"}, {"link": "http://www.pep.com.cn/oldimages/pic_133240.jpg", "page": 0, "title": "\u7b2c3\u8282\u9057\u4f20\u4fe1\u606f\u7684\u643a\u5e26\u8005"}, {"link": "http://www.pep.com.cn/oldimages/pic_133241.jpg", "page": 0, "title": "\u7b2c3\u8282\u9057\u4f20\u4fe1\u606f\u7684\u643a\u5e26\u8005"}, {"link": "http://www.pep.com.cn/oldimages/pic_133242.jpg", "page": 0, "title": "\u7b2c3\u8282\u9057\u4f20\u4fe1\u606f\u7684\u643a\u5e26\u8005"}, {"link": "http://www.pep.com.cn/gzsw/jshzhx/tbziy/kbshy/jsjb/bxyi/201009/W020100913380295154883.jpg", "page": 0, "title": "\u3000\u3000\u7b2c4\u8282\u3000\u7ec6\u80de\u4e2d\u7684\u7cd6\u7c7b\u548c\u8102\u8d28"}, {"link": "http://www.pep.com.cn/oldimages/pic_133244.jpg", "page": 0, "title": "\u7b2c4\u8282\u7ec6\u80de\u4e2d\u7684\u7cd6\u7c7b\u548c\u8102\u8d28\uff082\uff09"}, {"link": "http://www.pep.com.cn/oldimages/pic_133245.jpg", "page": 0, "title": "\u7b2c4\u8282\u7ec6\u80de\u4e2d\u7684\u7cd6\u7c7b\u548c\u8102\u8d28\uff083\uff09"}, {"link": "http://www.pep.com.cn/oldimages/pic_133246.jpg", "page": 0, "title": "\u7b2c4\u8282\u7ec6\u80de\u4e2d\u7684\u7cd6\u7c7b\u548c\u8102\u8d28\uff084\uff09"}, {"link": "http://www.pep.com.cn/gzsw/jshzhx/tbziy/kbshy/jsjb/bxyi/201009/W020100913380290305673.jpg", "page": 0, "title": "\u3000\u3000\u7b2c5\u8282\u3000\u7ec6\u80de\u4e2d\u7684\u65e0\u673a\u7269"}, {"link": "http://www.pep.com.cn/oldimages/pic_133248.jpg", "page": 0, "title": "\u7b2c5\u8282\u7ec6\u80de\u4e2d\u7684\u65e0\u673a\u7269\uff082\uff09"}, {"link": "http://www.pep.com.cn/oldimages/pic_133249.jpg", "page": 0, "title": "\u7b2c5\u8282\u7ec6\u80de\u4e2d\u7684\u65e0\u673a\u7269\uff083\uff09"}, {"link": "http://www.pep.com.cn/oldimages/pic_133250.jpg", "page": 0, "title": "\u672c\u7ae0\u5c0f\u7ed3"}, {"link": "http://www.pep.com.cn/oldimages/pic_133251.jpg", "page": 0, "title": "\u81ea\u6211\u68c0\u6d4b"}, {"link": "http://www.pep.com.cn/gzsw/jshzhx/tbziy/kbshy/jsjb/bxyi/201009/W020100913380284999879.jpg", "page": 0, "title": "<strong>\u7b2c3\u7ae0\u3000\u7ec6\u80de\u7684\u57fa\u672c\u7ed3\u6784</strong>"}, {"link": "http://www.pep.com.cn/gzsw/jshzhx/tbziy/kbshy/jsjb/bxyi/201009/W020100913380283434156.jpg", "page": 0, "title": "\u3000\u3000\u7b2c1\u8282\u3000\u7ec6\u80de\u819c\u2500\u2500\u7cfb\u7edf\u7684\u8fb9\u754c"}, {"link": "http://www.pep.com.cn/oldimages/pic_133254.jpg", "page": 0, "title": "\u7b2c1\u8282\u7ec6\u80de\u819c"}, {"link": "http://www.pep.com.cn/oldimages/pic_133255.jpg", "page": 0, "title": "\u7b2c1\u8282\u7ec6\u80de\u819c"}, {"link": "http://www.pep.com.cn/oldimages/pic_133256.jpg", "page": 0, "title": "\u7b2c1\u8282\u7ec6\u80de\u819c"}, {"link": "http://www.pep.com.cn/gzsw/jshzhx/tbziy/kbshy/jsjb/bxyi/201009/W020100913380278275212.jpg", "page": 0, "title": "\u3000\u3000\u7b2c2\u8282\u3000\u7ec6\u80de\u5668\u2500\u2500\u7cfb\u7edf\u5185\u7684\u5206\u5de5\u5408\u4f5c"}, {"link": "http://www.pep.com.cn/oldimages/pic_133258.jpg", "page": 0, "title": "\u7b2c2\u8282\u7ec6\u80de\u5668"}, {"link": "http://www.pep.com.cn/oldimages/pic_133259.jpg", "page": 0, "title": "\u7b2c2\u8282\u7ec6\u80de\u5668"}, {"link": "http://www.pep.com.cn/oldimages/pic_133260.jpg", "page": 0, "title": "\u7b2c2\u8282\u7ec6\u80de\u5668"}, {"link": "http://www.pep.com.cn/oldimages/pic_133261.jpg", "page": 0, "title": "\u7b2c2\u8282\u7ec6\u80de\u5668"}, {"link": "http://www.pep.com.cn/oldimages/pic_133262.jpg", "page": 0, "title": "\u7b2c2\u8282\u7ec6\u80de\u5668"}, {"link": "http://www.pep.com.cn/oldimages/pic_133263.jpg", "page": 0, "title": "\u7b2c2\u8282\u7ec6\u80de\u5668"}, {"link": "http://www.pep.com.cn/gzsw/jshzhx/tbziy/kbshy/jsjb/bxyi/201009/W020100913380270624209.jpg", "page": 0, "title": "\u3000\u3000\u79d1\u5b66\u5bb6\u7684\u6545\u4e8b\u3000\u7ec6\u80de\u4e16\u754c\u63a2\u5fae\u4e09\u4f8b"}, {"link": "http://www.pep.com.cn/gzsw/jshzhx/tbziy/kbshy/jsjb/bxyi/201009/W020100913380269052672.jpg", "page": 0, "title": "\u3000\u3000\u7b2c3\u8282\u3000\u7ec6\u80de\u6838\u2014\u2014\u7cfb\u7edf\u7684\u63a7\u5236\u4e2d\u5fc3"}, {"link": "http://www.pep.com.cn/oldimages/pic_133266.jpg", "page": 0, "title": "\u7b2c3\u8282\u7ec6\u80de\u6838"}, {"link": "http://www.pep.com.cn/oldimages/pic_133267.jpg", "page": 0, "title": "\u7b2c3\u8282\u7ec6\u80de\u6838"}, {"link": "http://www.pep.com.cn/oldimages/pic_133268.jpg", "page": 0, "title": "\u7b2c3\u8282\u7ec6\u80de\u6838"}, {"link": "http://www.pep.com.cn/oldimages/pic_133269.jpg", "page": 0, "title": "\u7b2c3\u8282\u7ec6\u80de\u6838"}, {"link": "http://www.pep.com.cn/oldimages/pic_133270.jpg", "page": 0, "title": "\u672c\u7ae0\u5c0f\u7ed3"}, {"link": "http://www.pep.com.cn/oldimages/pic_133271.jpg", "page": 0, "title": "\u81ea\u6211\u68c0\u6d4b"}, {"link": "http://www.pep.com.cn/gzsw/jshzhx/tbziy/kbshy/jsjb/bxyi/201009/W020100913380260774735.jpg", "page": 0, "title": "<strong>\u7b2c4\u7ae0\u3000\u7ec6\u80de\u7684\u7269\u8d28\u8f93\u5165\u548c\u8f93\u51fa</strong>"}, {"link": "http://www.pep.com.cn/gzsw/jshzhx/tbziy/kbshy/jsjb/bxyi/201009/W020100913380259524799.jpg", "page": 0, "title": "\u3000\u3000\u7b2c1\u8282\u3000\u7269\u8d28\u8de8\u819c\u8fd0\u8f93\u7684\u5b9e\u4f8b"}, {"link": "http://www.pep.com.cn/oldimages/pic_133274.jpg", "page": 0, "title": "\u7b2c1\u8282\u7269\u8d28\u8de8\u819c\u8fd0\u8f93\u7684\u5b9e\u4f8b\uff082\uff09"}, {"link": "http://www.pep.com.cn/oldimages/pic_133275.jpg", "page": 0, "title": "\u7b2c1\u8282\u7269\u8d28\u8de8\u819c\u8fd0\u8f93\u7684\u5b9e\u4f8b\uff083\uff09"}, {"link": "http://www.pep.com.cn/oldimages/pic_133276.jpg", "page": 0, "title": "\u7b2c1\u8282\u7269\u8d28\u8de8\u819c\u8fd0\u8f93\u7684\u5b9e\u4f8b\uff084\uff09"}, {"link": "http://www.pep.com.cn/oldimages/pic_133277.jpg", "page": 0, "title": "\u7b2c1\u8282\u7269\u8d28\u8de8\u819c\u8fd0\u8f93\u7684\u5b9e\u4f8b\uff085\uff09"}, {"link": "http://www.pep.com.cn/gzsw/jshzhx/tbziy/kbshy/jsjb/bxyi/201009/W020100913380242188209.jpg", "page": 0, "title": "\u3000\u3000\u7b2c2\u8282\u3000\u751f\u7269\u819c\u7684\u6d41\u52a8\u9576\u5d4c\u6a21\u578b"}, {"link": "http://www.pep.com.cn/oldimages/pic_133279.jpg", "page": 0, "title": "\u7b2c2\u8282\u751f\u7269\u819c\u7684\u6d41\u52a8\u9576\u5d4c\u6a21\u578b\uff082\uff09"}, {"link": "http://www.pep.com.cn/oldimages/pic_133280.jpg", "page": 0, "title": "\u7b2c2\u8282\u751f\u7269\u819c\u7684\u6d41\u52a8\u9576\u5d4c\u6a21\u578b\uff083\uff09"}, {"link": "http://www.pep.com.cn/oldimages/pic_133281.jpg", "page": 0, "title": "\u7b2c2\u8282\u751f\u7269\u819c\u7684\u6d41\u52a8\u9576\u5d4c\u6a21\u578b\uff084\uff09"}, {"link": "http://www.pep.com.cn/oldimages/pic_133282.jpg", "page": 0, "title": "\u7b2c2\u8282\u751f\u7269\u819c\u7684\u6d41\u52a8\u9576\u5d4c\u6a21\u578b\uff085\uff09"}, {"link": "http://www.pep.com.cn/gzsw/jshzhx/tbziy/kbshy/jsjb/bxyi/201009/W020100913380236560947.jpg", "page": 0, "title": "\u3000\u3000\u7b2c3\u8282\u3000\u7269\u8d28\u8de8\u819c\u8fd0\u8f93\u7684\u65b9\u5f0f"}, {"link": "http://www.pep.com.cn/oldimages/pic_133284.jpg", "page": 0, "title": "\u7b2c3\u8282\u7269\u8d28\u8de8\u819c\u8fd0\u8f93\u7684\u65b9\u5f0f\uff082\uff09"}, {"link": "http://www.pep.com.cn/oldimages/pic_133285.jpg", "page": 0, "title": "\u7b2c3\u8282\u7269\u8d28\u8de8\u819c\u8fd0\u8f93\u7684\u65b9\u5f0f\uff083\uff09"}, {"link": "http://www.pep.com.cn/oldimages/pic_133286.jpg", "page": 0, "title": "\u7b2c3\u8282\u7269\u8d28\u8de8\u819c\u8fd0\u8f93\u7684\u65b9\u5f0f\uff084\uff09"}, {"link": "http://www.pep.com.cn/gzsw/jshzhx/tbziy/kbshy/jsjb/bxyi/201009/W020100913380231712957.jpg", "page": 0, "title": "\u3000\u3000\u79d1\u5b66\u524d\u6cbf\u3000\u6388\u4e88\u8bfa\u8d1d\u5c14\u5316\u5b66\u5956\u7684\u901a\u9053\u86cb\u767d\u7814\u7a76"}, {"link": "http://www.pep.com.cn/oldimages/pic_133288.jpg", "page": 0, "title": "\u672c\u7ae0\u5c0f\u7ed3"}, {"link": "http://www.pep.com.cn/oldimages/pic_133289.jpg", "page": 0, "title": "\u81ea\u6211\u68c0\u6d4b"}, {"link": "http://www.pep.com.cn/gzsw/jshzhx/tbziy/kbshy/jsjb/bxyi/201009/W020100913380227651249.jpg", "page": 0, "title": "<strong>\u7b2c5\u7ae0\u3000\u7ec6\u80de\u7684\u80fd\u91cf\u4f9b\u5e94\u548c\u5229\u7528</strong>"}, {"link": "", "page": 0, "title": "\u3000\u3000\u7b2c1\u8282\u3000\u964d\u4f4e\u5316\u5b66\u53cd\u5e94\u6d3b\u5316\u80fd\u7684\u9176"}, {"link": "http://www.pep.com.cn/gzsw/jshzhx/tbziy/kbshy/jsjb/bxyi/201009/W020100913380226098486.jpg", "page": 0, "title": "\u3000\u3000\u4e00\u3000\u9176\u7684\u4f5c\u7528\u548c\u672c\u8d28</br>"}, {"link": "http://www.pep.com.cn/oldimages/pic_133292.jpg", "page": 0, "title": "\u4e00\u9176\u7684\u4f5c\u7528\u548c\u672c\u8d28\uff082\uff09"}, {"link": "http://www.pep.com.cn/oldimages/pic_133293.jpg", "page": 0, "title": "\u4e00\u9176\u7684\u4f5c\u7528\u548c\u672c\u8d28\uff083\uff09"}, {"link": "http://www.pep.com.cn/oldimages/pic_133294.jpg", "page": 0, "title": "\u4e00\u9176\u7684\u4f5c\u7528\u548c\u672c\u8d28\uff084\uff09"}, {"link": "http://www.pep.com.cn/oldimages/pic_133295.jpg", "page": 0, "title": "\u4e00\u9176\u7684\u4f5c\u7528\u548c\u672c\u8d28\uff085\uff09"}, {"link": "http://www.pep.com.cn/gzsw/jshzhx/tbziy/kbshy/jsjb/bxyi/201009/W020100913380220625473.jpg", "page": 0, "title": "\u3000\u3000\u4e8c\u3000\u9176\u7684\u7279\u6027"}, {"link": "http://www.pep.com.cn/oldimages/pic_133297.jpg", "page": 0, "title": "\u4e8c\u9176\u7684\u7279\u6027\uff082\uff09"}, {"link": "http://www.pep.com.cn/oldimages/pic_133298.jpg", "page": 0, "title": "\u4e8c\u9176\u7684\u7279\u6027\uff083\uff09"}, {"link": "http://www.pep.com.cn/oldimages/pic_133299.jpg", "page": 0, "title": "\u4e8c\u9176\u7684\u7279\u6027\uff084\uff09"}, {"link": "http://www.pep.com.cn/gzsw/jshzhx/tbziy/kbshy/jsjb/bxyi/201009/W020100913380215471948.jpg", "page": 0, "title": "\u3000\u3000\u79d1\u5b66\u00b7\u6280\u672f\u00b7\u793e\u4f1a\u3000\u9176\u4e3a\u751f\u6d3b\u6dfb\u59ff\u5f69"}, {"link": "http://www.pep.com.cn/gzsw/jshzhx/tbziy/kbshy/jsjb/bxyi/201009/W020100913380214063055.jpg", "page": 0, "title": "\u3000\u3000\u7b2c2\u8282\u3000\u7ec6\u80de\u7684\u80fd\u91cf\u201c\u901a\u8d27\u201d\u2500\u2500ATP"}, {"link": "http://www.pep.com.cn/oldimages/pic_133302.jpg", "page": 0, "title": "\u7b2c2\u8282\u7ec6\u80de\u7684\u80fd\u91cf\u201c\u901a\u8d27\u201d"}, {"link": "http://www.pep.com.cn/oldimages/pic_133303.jpg", "page": 0, "title": "\u7b2c2\u8282\u7ec6\u80de\u7684\u80fd\u91cf\u201c\u901a\u8d27\u201d"}, {"link": "http://www.pep.com.cn/gzsw/jshzhx/tbziy/kbshy/jsjb/bxyi/201009/W020100913380209225325.jpg", "page": 0, "title": "\u3000\u3000\u7b2c3\u8282\u3000ATP\u7684\u4e3b\u8981\u6765\u6e90\u2500\u2500\u7ec6\u80de\u547c\u5438"}, {"link": "http://www.pep.com.cn/oldimages/pic_133305.jpg", "page": 0, "title": "\u7b2c3\u8282ATP\u7684\u4e3b\u8981\u6765\u6e90"}, {"link": "http://www.pep.com.cn/oldimages/pic_133306.jpg", "page": 0, "title": "\u7b2c3\u8282ATP\u7684\u4e3b\u8981\u6765\u6e90"}, {"link": "http://www.pep.com.cn/oldimages/pic_133307.jpg", "page": 0, "title": "\u7b2c3\u8282ATP\u7684\u4e3b\u8981\u6765\u6e90"}, {"link": "http://www.pep.com.cn/oldimages/pic_133308.jpg", "page": 0, "title": "\u7b2c3\u8282ATP\u7684\u4e3b\u8981\u6765\u6e90"}, {"link": "http://www.pep.com.cn/oldimages/pic_133309.jpg", "page": 0, "title": "\u7b2c3\u8282ATP\u7684\u4e3b\u8981\u6765\u6e90"}, {"link": "", "page": 0, "title": "\u3000\u3000\u7b2c4\u8282\u3000\u80fd\u91cf\u4e4b\u6e90\u2500\u2500\u5149\u4e0e\u5149\u5408\u4f5c\u7528"}, {"link": "http://www.pep.com.cn/gzsw/jshzhx/tbziy/kbshy/jsjb/bxyi/201009/W020100913380202033231.jpg", "page": 0, "title": "\u3000\u3000\u4e00\u3000\u6355\u83b7\u5149\u80fd\u7684\u8272\u7d20\u548c\u7ed3\u6784</br>"}, {"link": "http://www.pep.com.cn/oldimages/pic_133311.jpg", "page": 0, "title": "\u4e00\u6355\u83b7\u5149\u80fd\u7684\u8272\u7d20\u548c\u7ed3\u6784\uff082\uff09"}, {"link": "http://www.pep.com.cn/oldimages/pic_133312.jpg", "page": 0, "title": "\u4e00\u6355\u83b7\u5149\u80fd\u7684\u8272\u7d20\u548c\u7ed3\u6784\uff083\uff09"}, {"link": "http://www.pep.com.cn/oldimages/pic_133313.jpg", "page": 0, "title": "\u4e00\u6355\u83b7\u5149\u80fd\u7684\u8272\u7d20\u548c\u7ed3\u6784\uff084\uff09"}, {"link": "http://www.pep.com.cn/gzsw/jshzhx/tbziy/kbshy/jsjb/bxyi/201009/W020100913380196563691.jpg", "page": 0, "title": "\u3000\u3000\u4e8c\u3000\u5149\u5408\u4f5c\u7528\u7684\u539f\u7406\u548c\u5e94\u7528"}, {"link": "http://www.pep.com.cn/oldimages/pic_133315.jpg", "page": 0, "title": "\u4e8c\u5149\u5408\u4f5c\u7528\u7684\u539f\u7406\u548c\u5e94\u7528\uff082\uff09"}, {"link": "http://www.pep.com.cn/oldimages/pic_133316.jpg", "page": 0, "title": "\u4e8c\u5149\u5408\u4f5c\u7528\u7684\u539f\u7406\u548c\u5e94\u7528\uff083\uff09"}, {"link": "http://www.pep.com.cn/oldimages/pic_133317.jpg", "page": 0, "title": "\u4e8c\u5149\u5408\u4f5c\u7528\u7684\u539f\u7406\u548c\u5e94\u7528\uff084\uff09"}, {"link": "http://www.pep.com.cn/oldimages/pic_133318.jpg", "page": 0, "title": "\u4e8c\u5149\u5408\u4f5c\u7528\u7684\u539f\u7406\u548c\u5e94\u7528\uff085\uff09"}, {"link": "http://www.pep.com.cn/oldimages/pic_133319.jpg", "page": 0, "title": "\u4e8c\u5149\u5408\u4f5c\u7528\u7684\u539f\u7406\u548c\u5e94\u7528\uff086\uff09"}, {"link": "http://www.pep.com.cn/oldimages/pic_133320.jpg", "page": 0, "title": "\u672c\u7ae0\u5c0f\u7ed3"}, {"link": "http://www.pep.com.cn/oldimages/pic_133321.jpg", "page": 0, "title": "\u81ea\u6211\u68c0\u6d4b"}, {"link": "http://www.pep.com.cn/gzsw/jshzhx/tbziy/kbshy/jsjb/bxyi/201009/W020100913380179383706.jpg", "page": 0, "title": "\u3000\u3000\u7b2c1\u8282\u3000\u7ec6\u80de\u7684\u589e\u6b96"}, {"link": "http://www.pep.com.cn/oldimages/pic_135224.jpg", "page": 0, "title": "\u7b2c1\u8282\u7ec6\u80de\u7684\u589e\u6b96\uff082\uff09"}, {"link": "http://www.pep.com.cn/oldimages/pic_135225.jpg", "page": 0, "title": "\u7b2c1\u8282\u7ec6\u80de\u7684\u589e\u6b96\uff083\uff09"}, {"link": "http://www.pep.com.cn/oldimages/pic_135226.jpg", "page": 0, "title": "\u7b2c1\u8282\u7ec6\u80de\u7684\u589e\u6b96\uff084\uff09"}, {"link": "http://www.pep.com.cn/oldimages/pic_135227.jpg", "page": 0, "title": "\u7b2c1\u8282\u7ec6\u80de\u7684\u589e\u6b96\uff085\uff09"}, {"link": "http://www.pep.com.cn/oldimages/pic_135228.jpg", "page": 0, "title": "\u7b2c1\u8282\u7ec6\u80de\u7684\u589e\u6b96\uff086\uff09"}, {"link": "http://www.pep.com.cn/oldimages/pic_135229.jpg", "page": 0, "title": "\u7b2c1\u8282\u7ec6\u80de\u7684\u589e\u6b96\uff087\uff09"}, {"link": "http://www.pep.com.cn/oldimages/pic_135245.jpg", "page": 0, "title": "\u7b2c1\u8282\u7ec6\u80de\u7684\u589e\u6b96\uff088\uff09"}, {"link": "http://www.pep.com.cn/oldimages/pic_135225.jpg", "page": 0, "title": "\u7b2c1\u8282\u7ec6\u80de\u7684\u589e\u6b96\uff089\uff09"}, {"link": "http://www.pep.com.cn/oldimages/pic_135226.jpg", "page": 0, "title": "\u7b2c1\u8282\u7ec6\u80de\u7684\u589e\u6b96\uff0810\uff09"}, {"link": "http://www.pep.com.cn/oldimages/pic_135227.jpg", "page": 0, "title": "\u7b2c1\u8282\u7ec6\u80de\u7684\u589e\u6b96\uff0811\uff09"}, {"link": "http://www.pep.com.cn/oldimages/pic_135228.jpg", "page": 0, "title": "\u7b2c1\u8282\u7ec6\u80de\u7684\u589e\u6b96\uff0812\uff09"}, {"link": "http://www.pep.com.cn/oldimages/pic_135229.jpg", "page": 0, "title": "\u7b2c1\u8282\u7ec6\u80de\u7684\u589e\u6b96\uff0813\uff09"}, {"link": "http://www.pep.com.cn/gzsw/jshzhx/tbziy/kbshy/jsjb/bxyi/201009/W020100913380164228907.jpg", "page": 0, "title": "\u3000\u3000\u7b2c2\u8282\u3000\u7ec6\u80de\u7684\u5206\u5316"}, {"link": "http://www.pep.com.cn/oldimages/pic_135266.jpg", "page": 0, "title": "\u7b2c2\u8282\u7ec6\u80de\u7684\u5206\u5316\uff082\uff09"}, {"link": "http://www.pep.com.cn/oldimages/pic_135232.jpg", "page": 0, "title": "\u7b2c2\u8282\u7ec6\u80de\u7684\u5206\u5316\uff083\uff09"}, {"link": "http://www.pep.com.cn/oldimages/pic_135233.jpg", "page": 0, "title": "\u7b2c2\u8282\u7ec6\u80de\u7684\u5206\u5316\uff084\uff09"}, {"link": "http://www.pep.com.cn/gzsw/jshzhx/tbziy/kbshy/jsjb/bxyi/201009/W020100913380159534668.jpg", "page": 0, "title": "\u3000\u3000\u7b2c3\u8282\u3000\u7ec6\u80de\u7684\u8870\u8001\u548c\u51cb\u4ea1"}, {"link": "http://www.pep.com.cn/oldimages/pic_135235.jpg", "page": 0, "title": "\u7b2c3\u8282\u7ec6\u80de\u7684\u8870\u8001\u548c\u51cb\u4ea1\uff082\uff09"}, {"link": "http://www.pep.com.cn/oldimages/pic_135236.jpg", "page": 0, "title": "\u7b2c3\u8282\u7ec6\u80de\u7684\u8870\u8001\u548c\u51cb\u4ea1\uff083\uff09"}, {"link": "http://www.pep.com.cn/oldimages/pic_135237.jpg", "page": 0, "title": "\u7b2c3\u8282\u7ec6\u80de\u7684\u8870\u8001\u548c\u51cb\u4ea1\uff084\uff09"}, {"link": "http://www.pep.com.cn/gzsw/jshzhx/tbziy/kbshy/jsjb/bxyi/201009/W020100913380155312017.jpg", "page": 0, "title": "\u3000\u3000\u7b2c4\u8282\u3000\u7ec6\u80de\u7684\u764c\u53d8"}, {"link": "http://www.pep.com.cn/oldimages/pic_135239.jpg", "page": 0, "title": "\u7b2c4\u8282\u7ec6\u80de\u7684\u764c\u53d8\uff082\uff09"}, {"link": "http://www.pep.com.cn/oldimages/pic_135240.jpg", "page": 0, "title": "\u7b2c4\u8282\u7ec6\u80de\u7684\u764c\u53d8\uff083\uff09"}, {"link": "http://www.pep.com.cn/gzsw/jshzhx/tbziy/kbshy/jsjb/bxyi/201009/W020100913380143919164.jpg", "page": 0, "title": "\u3000\u3000\u4e0e\u751f\u7269\u5b66\u6709\u5173\u7684\u804c\u4e1a\u3000\u533b\u9662\u91cc\u7684\u68c0\u9a8c\u5e08"}, {"link": "http://www.pep.com.cn/oldimages/pic_135242.jpg", "page": 0, "title": "\u672c\u7ae0\u5c0f\u7ed3"}, {"link": "http://www.pep.com.cn/oldimages/pic_135243.jpg", "page": 0, "title": "\u81ea\u6211\u68c0\u6d4b"}, {"link": "http://www.pep.com.cn/oldimages/pic_135244.jpg", "page": 0, "title": "\u540e\u8bb0"}]}