{"name": "\u4e94\u5e74\u7ea7\u4e0b\u518c", "pages": [{"link": "http://www.pep.com.cn/oldimages/pic_255253.jpg", "page": 0, "title": "\u6249\u9875"}, {"link": "http://www.pep.com.cn/xe/jszx/tbjxzy/dzkb/xqddzkb/xqddzkb5x/201008/W020100827523457155537.jpg", "page": 0, "title": "\u8bf4\u660e"}, {"link": "http://www.pep.com.cn/xe/jszx/tbjxzy/dzkb/xqddzkb/xqddzkb5x/201008/W020100827523431375472.jpg", "page": 0, "title": "\u8bf4\u660e(2)"}, {"link": "http://www.pep.com.cn/oldimages/pic_255255.jpg", "page": 0, "title": "\u7f16\u5199\u4eba\u5458"}, {"link": "http://www.pep.com.cn/oldimages/pic_255258.jpg", "page": 0, "title": "\u76ee\u5f55\u9875"}, {"link": "http://www.pep.com.cn/xe/jszx/tbjxzy/dzkb/xqddzkb/xqddzkb5x/201008/W020100827523341523824.jpg", "page": 0, "title": "\u7248\u6743\u9875"}, {"link": "http://www.pep.com.cn/oldimages/pic_255259.jpg", "page": 0, "title": "CharactersofThisBook"}, {"link": "http://www.pep.com.cn/oldimages/pic_255260.jpg", "page": 0, "title": "Unit 9 How Often Do You Go There? "}, {"link": "http://www.pep.com.cn/oldimages/pic_255261.jpg", "page": 0, "title": "Lesson49(2)"}, {"link": "http://www.pep.com.cn/oldimages/pic_255262.jpg", "page": 0, "title": "Lesson50"}, {"link": "http://www.pep.com.cn/oldimages/pic_255263.jpg", "page": 0, "title": "Lesson50(2)"}, {"link": "http://www.pep.com.cn/oldimages/pic_255264.jpg", "page": 0, "title": "Lesson51"}, {"link": "http://www.pep.com.cn/oldimages/pic_255265.jpg", "page": 0, "title": "Lesson51(2)"}, {"link": "http://www.pep.com.cn/oldimages/pic_255266.jpg", "page": 0, "title": "Lesson52"}, {"link": "http://www.pep.com.cn/oldimages/pic_255267.jpg", "page": 0, "title": "Lesson52(2)"}, {"link": "http://www.pep.com.cn/oldimages/pic_255268.jpg", "page": 0, "title": "Lesson53"}, {"link": "http://www.pep.com.cn/oldimages/pic_255269.jpg", "page": 0, "title": "Lesson53(2)"}, {"link": "http://www.pep.com.cn/oldimages/pic_255270.jpg", "page": 0, "title": "Lesson54"}, {"link": "http://www.pep.com.cn/oldimages/pic_255271.jpg", "page": 0, "title": "Lesson54(2)"}, {"link": "http://www.pep.com.cn/oldimages/pic_255272.jpg", "page": 0, "title": "Unit 10 Doing Things "}, {"link": "http://www.pep.com.cn/oldimages/pic_255273.jpg", "page": 0, "title": "Lesson55(2)"}, {"link": "http://www.pep.com.cn/oldimages/pic_255274.jpg", "page": 0, "title": "Lesson56"}, {"link": "http://www.pep.com.cn/oldimages/pic_255275.jpg", "page": 0, "title": "Lesson56(2)"}, {"link": "http://www.pep.com.cn/oldimages/pic_255276.jpg", "page": 0, "title": "Lesson57"}, {"link": "http://www.pep.com.cn/oldimages/pic_255277.jpg", "page": 0, "title": "Lesson57(2)"}, {"link": "http://www.pep.com.cn/oldimages/pic_255278.jpg", "page": 0, "title": "Lesson58"}, {"link": "http://www.pep.com.cn/oldimages/pic_255279.jpg", "page": 0, "title": "Lesson58(2)"}, {"link": "http://www.pep.com.cn/oldimages/pic_255280.jpg", "page": 0, "title": "Lesson59"}, {"link": "http://www.pep.com.cn/oldimages/pic_255281.jpg", "page": 0, "title": "Lesson59(2)"}, {"link": "http://www.pep.com.cn/oldimages/pic_255282.jpg", "page": 0, "title": "Lesson60"}, {"link": "http://www.pep.com.cn/oldimages/pic_255283.jpg", "page": 0, "title": "Lesson60(2)"}, {"link": "http://www.pep.com.cn/oldimages/pic_255284.jpg", "page": 0, "title": "Unit 11 Keeping Fit "}, {"link": "http://www.pep.com.cn/oldimages/pic_255285.jpg", "page": 0, "title": "Lesson61(2)"}, {"link": "http://www.pep.com.cn/oldimages/pic_255286.jpg", "page": 0, "title": "Lesson62"}, {"link": "http://www.pep.com.cn/oldimages/pic_255287.jpg", "page": 0, "title": "Lesson62(2)"}, {"link": "http://www.pep.com.cn/oldimages/pic_255288.jpg", "page": 0, "title": "Lesson63"}, {"link": "http://www.pep.com.cn/oldimages/pic_255289.jpg", "page": 0, "title": "Lesson63(2)"}, {"link": "http://www.pep.com.cn/oldimages/pic_255290.jpg", "page": 0, "title": "Lesson64"}, {"link": "http://www.pep.com.cn/oldimages/pic_255291.jpg", "page": 0, "title": "Lesson64(2)"}, {"link": "http://www.pep.com.cn/oldimages/pic_255292.jpg", "page": 0, "title": "Lesson65"}, {"link": "http://www.pep.com.cn/oldimages/pic_255293.jpg", "page": 0, "title": "Lesson65(2)"}, {"link": "http://www.pep.com.cn/oldimages/pic_255294.jpg", "page": 0, "title": "Lesson66"}, {"link": "http://www.pep.com.cn/oldimages/pic_255295.jpg", "page": 0, "title": "Lesson66(2)"}, {"link": "http://www.pep.com.cn/oldimages/pic_255296.jpg", "page": 0, "title": "Unit 12 Revision "}, {"link": "http://www.pep.com.cn/oldimages/pic_255297.jpg", "page": 0, "title": "Lesson68"}, {"link": "http://www.pep.com.cn/oldimages/pic_255298.jpg", "page": 0, "title": "Lesson69"}, {"link": "http://www.pep.com.cn/oldimages/pic_255299.jpg", "page": 0, "title": "Lesson69(2)"}, {"link": "http://www.pep.com.cn/oldimages/pic_255300.jpg", "page": 0, "title": "Lesson70"}, {"link": "http://www.pep.com.cn/oldimages/pic_255301.jpg", "page": 0, "title": "Lesson70(2)"}, {"link": "http://www.pep.com.cn/oldimages/pic_255302.jpg", "page": 0, "title": "Lesson71"}, {"link": "http://www.pep.com.cn/oldimages/pic_255303.jpg", "page": 0, "title": "Lesson71(2)"}, {"link": "http://www.pep.com.cn/oldimages/pic_255304.jpg", "page": 0, "title": "Lesson72"}, {"link": "http://www.pep.com.cn/oldimages/pic_255305.jpg", "page": 0, "title": "Lesson72(2)"}, {"link": "http://www.pep.com.cn/oldimages/pic_255306.jpg", "page": 0, "title": "Unit 13 Last weekend "}, {"link": "http://www.pep.com.cn/oldimages/pic_255307.jpg", "page": 0, "title": "Lesson73(2)"}, {"link": "http://www.pep.com.cn/oldimages/pic_255308.jpg", "page": 0, "title": "Lesson74"}, {"link": "http://www.pep.com.cn/oldimages/pic_255309.jpg", "page": 0, "title": "Lesson74(2)"}, {"link": "http://www.pep.com.cn/oldimages/pic_255310.jpg", "page": 0, "title": "Lesson75"}, {"link": "http://www.pep.com.cn/oldimages/pic_255311.jpg", "page": 0, "title": "Lesson75(2)"}, {"link": "http://www.pep.com.cn/oldimages/pic_255312.jpg", "page": 0, "title": "Lesson76"}, {"link": "http://www.pep.com.cn/oldimages/pic_255313.jpg", "page": 0, "title": "Lesson76(2)"}, {"link": "http://www.pep.com.cn/oldimages/pic_255314.jpg", "page": 0, "title": "Lesson77"}, {"link": "http://www.pep.com.cn/oldimages/pic_255315.jpg", "page": 0, "title": "Lesson77(2)"}, {"link": "http://www.pep.com.cn/oldimages/pic_255316.jpg", "page": 0, "title": "Lesson78"}, {"link": "http://www.pep.com.cn/oldimages/pic_255317.jpg", "page": 0, "title": "Lesson78(2)"}, {"link": "http://www.pep.com.cn/oldimages/pic_255318.jpg", "page": 0, "title": "Unit 14 A Great Trip  "}, {"link": "http://www.pep.com.cn/oldimages/pic_255319.jpg", "page": 0, "title": "Lesson79(2)"}, {"link": "http://www.pep.com.cn/oldimages/pic_255320.jpg", "page": 0, "title": "Lesson80"}, {"link": "http://www.pep.com.cn/oldimages/pic_255321.jpg", "page": 0, "title": "Lesson80(2)"}, {"link": "http://www.pep.com.cn/oldimages/pic_255322.jpg", "page": 0, "title": "Lesson81"}, {"link": "http://www.pep.com.cn/oldimages/pic_255323.jpg", "page": 0, "title": "Lesson81(2)"}, {"link": "http://www.pep.com.cn/oldimages/pic_255324.jpg", "page": 0, "title": "Lesson82"}, {"link": "http://www.pep.com.cn/oldimages/pic_255325.jpg", "page": 0, "title": "Lesson82(2)"}, {"link": "http://www.pep.com.cn/oldimages/pic_255326.jpg", "page": 0, "title": "Lesson83"}, {"link": "http://www.pep.com.cn/oldimages/pic_255327.jpg", "page": 0, "title": "Lesson83(2)"}, {"link": "http://www.pep.com.cn/oldimages/pic_255328.jpg", "page": 0, "title": "Lesson84"}, {"link": "http://www.pep.com.cn/oldimages/pic_255329.jpg", "page": 0, "title": "Lesson84(2)"}, {"link": "http://www.pep.com.cn/oldimages/pic_255330.jpg", "page": 0, "title": "Unit 15 Growing Up "}, {"link": "http://www.pep.com.cn/oldimages/pic_255331.jpg", "page": 0, "title": "Lesson85(2)"}, {"link": "http://www.pep.com.cn/oldimages/pic_255332.jpg", "page": 0, "title": "Lesson86"}, {"link": "http://www.pep.com.cn/oldimages/pic_255333.jpg", "page": 0, "title": "Lesson86(2)"}, {"link": "http://www.pep.com.cn/oldimages/pic_255334.jpg", "page": 0, "title": "Lesson87"}, {"link": "http://www.pep.com.cn/oldimages/pic_255335.jpg", "page": 0, "title": "Lesson87(2)"}, {"link": "http://www.pep.com.cn/oldimages/pic_255336.jpg", "page": 0, "title": "Lesson88"}, {"link": "http://www.pep.com.cn/oldimages/pic_255337.jpg", "page": 0, "title": "Lesson88(2)"}, {"link": "http://www.pep.com.cn/oldimages/pic_255338.jpg", "page": 0, "title": "Lesson89"}, {"link": "http://www.pep.com.cn/oldimages/pic_255339.jpg", "page": 0, "title": "Lesson89(2)"}, {"link": "http://www.pep.com.cn/oldimages/pic_255340.jpg", "page": 0, "title": "Lesson90"}, {"link": "http://www.pep.com.cn/oldimages/pic_255342.jpg", "page": 0, "title": "Lesson90(2)"}, {"link": "http://www.pep.com.cn/oldimages/pic_255341.jpg", "page": 0, "title": "Unit 16 Revision "}, {"link": "http://www.pep.com.cn/oldimages/pic_255343.jpg", "page": 0, "title": "Lesson92"}, {"link": "http://www.pep.com.cn/oldimages/pic_255344.jpg", "page": 0, "title": "Lesson93"}, {"link": "http://www.pep.com.cn/oldimages/pic_255345.jpg", "page": 0, "title": "Lesson93(2)"}, {"link": "http://www.pep.com.cn/oldimages/pic_255346.jpg", "page": 0, "title": "Lesson94"}, {"link": "http://www.pep.com.cn/oldimages/pic_255347.jpg", "page": 0, "title": "Lesson94(2)"}, {"link": "http://www.pep.com.cn/oldimages/pic_255348.jpg", "page": 0, "title": "Lesson95"}, {"link": "http://www.pep.com.cn/oldimages/pic_255349.jpg", "page": 0, "title": "Lesson95(2)"}, {"link": "http://www.pep.com.cn/oldimages/pic_255350.jpg", "page": 0, "title": "Lesson96"}, {"link": "http://www.pep.com.cn/oldimages/pic_255351.jpg", "page": 0, "title": "Lesson96(2)"}, {"link": "http://www.pep.com.cn/oldimages/pic_255352.jpg", "page": 0, "title": "\u9644\u5f55\u4e00 \u8bcd\u6c47\u8868\u4e00"}, {"link": "http://www.pep.com.cn/oldimages/pic_255353.jpg", "page": 0, "title": "\u8bcd\u6c47\u8868\u4e00(2)"}, {"link": "http://www.pep.com.cn/oldimages/pic_255354.jpg", "page": 0, "title": "\u8bcd\u6c47\u8868\u4e00(3)"}, {"link": "http://www.pep.com.cn/oldimages/pic_255355.jpg", "page": 0, "title": "\u9644\u5f55\u4e8c \u8bcd\u6c47\u8868\u4e8c"}, {"link": "http://www.pep.com.cn/oldimages/pic_255356.jpg", "page": 0, "title": "\u8bcd\u6c47\u8868\u4e8c(2)"}, {"link": "http://www.pep.com.cn/oldimages/pic_255357.jpg", "page": 0, "title": "\u8bcd\u6c47\u8868\u4e8c(3)"}, {"link": "http://www.pep.com.cn/oldimages/pic_255358.jpg", "page": 0, "title": "\u9644\u5f55\u4e09"}]}